ensembl_map/__init__.py
ensembl_map/convert.py
ensembl_map/ensembl.py
ensembl_map/exceptions.py
ensembl_map/features.py
ensembl_map/mapper.py
ensembl_map/sequence.py
ensembl_map/symbol.py
ensembl_map/util.py
ensembl_map-1.2.0.dist-info/LICENSE
ensembl_map-1.2.0.dist-info/METADATA
ensembl_map-1.2.0.dist-info/WHEEL
ensembl_map-1.2.0.dist-info/top_level.txt
ensembl_map-1.2.0.dist-info/RECORD
