Metadata-Version: 2.1
Name: ensembl-map
Version: 1.2.0
Summary: Convert between chromosome, gene, transcript, exon, CDS, and protein coordinates.
Home-page: https://github.com/mattdoug604/ensembl_map.git
Author: mattdoug604
Author-email: mattdoug604@gmail.com
License: https://spdx.org/licenses/MIT.html
Platform: UNKNOWN
Classifier: Development Status :: 3 - Alpha
Classifier: Environment :: Console
Classifier: Intended Audience :: Science/Research
Classifier: License :: OSI Approved :: MIT License
Classifier: Operating System :: OS Independent
Classifier: Programming Language :: Python
Classifier: Topic :: Scientific/Engineering :: Bio-Informatics
Requires-Python: >=3
Requires-Dist: pyensembl (>=1.8.5)
